tar_mak_unique_character_counter/__init__.py
tar_mak_unique_character_counter/task3_collections.py
tar_mak_unique_character_counter-1.3.0.dist-info/LICENSE
tar_mak_unique_character_counter-1.3.0.dist-info/METADATA
tar_mak_unique_character_counter-1.3.0.dist-info/WHEEL
tar_mak_unique_character_counter-1.3.0.dist-info/entry_points.txt
tar_mak_unique_character_counter-1.3.0.dist-info/top_level.txt
tar_mak_unique_character_counter-1.3.0.dist-info/RECORD
